[
    {
        "id": 1,
        "name": "Password Generator",
        "link": "https://scottkumor.github.io/Password-Generator/",
        "alt": "Password Generator",
        "title": "Password Generator",
        "description": "A lightweight random character generator for use when you need a new password.",
        "icon":"key"
    },
    {
        "id": 2,
        "name": "Day Planner",
        "link": "https://scottkumor.github.io/Day-Planner/",
        "alt": "Day Planner",
        "title": "Day Planner",
        "description": "A useful tool to help you plan your day.",
        "icon":"list-alt"
    },
    {
        "id": 3,
        "name": "Weather Dashboard",
        "link": "https://scottkumor.github.io/Weather-Dashboard/",
        "alt": "Weather Dashboard",
        "title": "Weather Dashboard",
        "description": "Find out the weather by typing in your city.",
        "icon":"cloud-sun-rain"
    },
    {
        "id": 4,
        "name": "uCTAnon",
        "link": "http://uctanon.herokuapp.com/",
        "alt": "uCTAnon",
        "title": "uCTAnon",
        "description": "Collaboration: Stay informed on the wild west that is Chicago's public rail system.",
        "icon":"subway"
    }
]
